gha_deploy/__init__.py
gha_deploy/cli.py
gha_deploy/github_api.py
gha_deploy-0.1.2.dist-info/METADATA
gha_deploy-0.1.2.dist-info/WHEEL
gha_deploy-0.1.2.dist-info/entry_points.txt
gha_deploy-0.1.2.dist-info/top_level.txt
gha_deploy-0.1.2.dist-info/RECORD
