Metadata-Version: 2.4
Name: gha-deploy
Version: 0.1.2
License: MIT
Project-URL: Homepage, https://github.com/ktierney15/gha-deploy-cli
Project-URL: Repository, https://github.com/ktierney15/gha-deploy-cli
Project-URL: Issues, https://github.com/ktierney15/gha-deploy-cli/issues
Requires-Python: >=3.8
Requires-Dist: click>=8.1
Requires-Dist: requests>=2.28
Requires-Dist: rich>=13.0
Requires-Dist: pylint
Requires-Dist: pytest
